ipymesh/__init__.py
ipymesh/_frontend.py
ipymesh/_version.py
ipymesh/pslg.py
ipymesh/labextension/ipymesh-widgets-0.1.1.tgz
ipymesh/labextension/ipymesh-widgets-0.1.2.tgz
ipymesh/labextension/ipymesh-widgets-0.1.3.tgz
ipymesh/labextension/ipymesh-widgets-0.1.4.tgz
ipymesh/labextension/ipymesh-widgets-0.1.5.tgz
ipymesh/labextension/ipymesh-widgets-0.1.6.tgz
ipymesh/labextension/ipymesh-widgets-0.1.7.tgz
ipymesh/nbextension/__init__.py
ipymesh/nbextension/static/extension.js
ipymesh/nbextension/static/index.js
ipymesh/nbextension/static/index.js.map
ipymesh-0.1.7.data/data/etc/jupyter/nbconfig/notebook.d/ipymesh.json
ipymesh-0.1.7.data/data/share/jupyter/lab/extensions/ipymesh-widgets-0.1.7.tgz
ipymesh-0.1.7.data/data/share/jupyter/nbextensions/ipymesh/extension.js
ipymesh-0.1.7.data/data/share/jupyter/nbextensions/ipymesh/index.js
ipymesh-0.1.7.data/data/share/jupyter/nbextensions/ipymesh/index.js.map
ipymesh-0.1.7.dist-info/LICENSE.txt
ipymesh-0.1.7.dist-info/METADATA
ipymesh-0.1.7.dist-info/WHEEL
ipymesh-0.1.7.dist-info/top_level.txt
ipymesh-0.1.7.dist-info/RECORD
